README.md
setup.py
joblist/Lookup_data_new_v2.pickle
joblist/__init__.py
joblist/dep.py
joblist/htmls.py
joblist/lookupcheck.py
joblist/mdr.py
joblist/trees.py
joblist/trees_cython.pyd
joblist/trees_cython.pyx
joblist.egg-info/PKG-INFO
joblist.egg-info/SOURCES.txt
joblist.egg-info/dependency_links.txt
joblist.egg-info/requires.txt
joblist.egg-info/top_level.txt