Metadata-Version: 1.0
Name: joblist
Version: 2.0.3
Summary: A Python implementation of joblist
Home-page: UNKNOWN
Author: Sellamani
Author-email: mail2.sella@gmail.com
License: UNKNOWN
Platform: UNKNOWN
